{"raids":[{"absoluteLastTime":1756183541,"lastRaidMap":"Ground Zero - Low","lastRaidAs":"PMC","raidResult":"Survived","raidKills":1,"bossesKilled":0,"scavsKilled":0,"raidDamage":101,"raidTime":2037,"discFromRaid":false,"isTransition":false,"lastRaidTransitionTo":"None","lastRaidEXP":1927,"lastRaidHits":4,"agressorName":"","lastRaidRanThrough":false,"lastRaidSurvived":1,"lcPointsEarned":54},{"absoluteLastTime":1756264011,"lastRaidMap":"Reserve","lastRaidAs":"SCAV","raidResult":"Killed","raidKills":0,"bossesKilled":0,"scavsKilled":0,"raidDamage":287,"raidTime":105,"discFromRaid":false,"isTransition":false,"lastRaidTransitionTo":"None","lastRaidEXP":0,"lastRaidHits":11,"agressorName":"VirtualHex","lastRaidRanThrough":false,"lastRaidSurvived":0,"lcPointsEarned":17},{"absoluteLastTime":1756266226,"lastRaidMap":"Ground Zero - Low","lastRaidAs":"PMC","raidResult":"Survived","raidKills":0,"bossesKilled":0,"scavsKilled":7,"raidDamage":362,"raidTime":2063,"discFromRaid":false,"isTransition":false,"lastRaidTransitionTo":"None","lastRaidEXP":2040,"lastRaidHits":14,"agressorName":"","lastRaidRanThrough":false,"lastRaidSurvived":1,"lcPointsEarned":67},{"absoluteLastTime":1756267178,"lastRaidMap":"Factory","lastRaidAs":"SCAV","raidResult":"Killed","raidKills":0,"bossesKilled":0,"scavsKilled":0,"raidDamage":220,"raidTime":48,"discFromRaid":false,"isTransition":false,"lastRaidTransitionTo":"None","lastRaidEXP":0,"lastRaidHits":8,"agressorName":"Queen-Goddess","lastRaidRanThrough":false,"lastRaidSurvived":0,"lcPointsEarned":16},{"absoluteLastTime":1756270160,"lastRaidMap":"Customs","lastRaidAs":"PMC","raidResult":"Survived","raidKills":2,"bossesKilled":0,"scavsKilled":6,"raidDamage":949,"raidTime":2215,"discFromRaid":false,"isTransition":false,"lastRaidTransitionTo":"None","lastRaidEXP":1822,"lastRaidHits":29,"agressorName":"","lastRaidRanThrough":false,"lastRaidSurvived":1,"lcPointsEarned":75},{"absoluteLastTime":1756338003,"lastRaidMap":"Ground Zero - Low","lastRaidAs":"PMC","raidResult":"Survived","raidKills":1,"bossesKilled":0,"scavsKilled":4,"raidDamage":400,"raidTime":2012,"discFromRaid":false,"isTransition":false,"lastRaidTransitionTo":"None","lastRaidEXP":1683,"lastRaidHits":11,"agressorName":"","lastRaidRanThrough":false,"lastRaidSurvived":1,"lcPointsEarned":63},{"absoluteLastTime":1756339222,"lastRaidMap":"Factory","lastRaidAs":"SCAV","raidResult":"Survived","raidKills":2,"bossesKilled":0,"scavsKilled":0,"raidDamage":41,"raidTime":674,"discFromRaid":false,"isTransition":false,"lastRaidTransitionTo":"None","lastRaidEXP":0,"lastRaidHits":3,"agressorName":"","lastRaidRanThrough":false,"lastRaidSurvived":1,"lcPointsEarned":76},{"absoluteLastTime":1756342534,"lastRaidMap":"Customs","lastRaidAs":"PMC","raidResult":"Survived","raidKills":0,"bossesKilled":0,"scavsKilled":1,"raidDamage":306,"raidTime":1997,"discFromRaid":false,"isTransition":false,"lastRaidTransitionTo":"None","lastRaidEXP":1345,"lastRaidHits":8,"agressorName":"","lastRaidRanThrough":false,"lastRaidSurvived":1,"lcPointsEarned":52},{"absoluteLastTime":1756344740,"lastRaidMap":"Reserve","lastRaidAs":"SCAV","raidResult":"Survived","raidKills":1,"bossesKilled":0,"scavsKilled":0,"raidDamage":34,"raidTime":977,"discFromRaid":false,"isTransition":false,"lastRaidTransitionTo":"None","lastRaidEXP":0,"lastRaidHits":1,"agressorName":"","lastRaidRanThrough":false,"lastRaidSurvived":1,"lcPointsEarned":59},{"absoluteLastTime":1756348409,"lastRaidMap":"Woods","lastRaidAs":"PMC","raidResult":"Survived","raidKills":1,"bossesKilled":0,"scavsKilled":4,"raidDamage":174,"raidTime":2333,"discFromRaid":false,"isTransition":false,"lastRaidTransitionTo":"None","lastRaidEXP":1896,"lastRaidHits":6,"agressorName":"","lastRaidRanThrough":false,"lastRaidSurvived":1,"lcPointsEarned":69},{"absoluteLastTime":1756351544,"lastRaidMap":"Ground Zero - Low","lastRaidAs":"PMC","raidResult":"Survived","raidKills":1,"bossesKilled":0,"scavsKilled":10,"raidDamage":1495,"raidTime":1655,"discFromRaid":false,"isTransition":false,"lastRaidTransitionTo":"None","lastRaidEXP":2012,"lastRaidHits":53,"agressorName":"","lastRaidRanThrough":false,"lastRaidSurvived":1,"lcPointsEarned":70},{"absoluteLastTime":1756355148,"lastRaidMap":"Customs","lastRaidAs":"PMC","raidResult":"Survived","raidKills":1,"bossesKilled":0,"scavsKilled":7,"raidDamage":806,"raidTime":2117,"discFromRaid":false,"isTransition":false,"lastRaidTransitionTo":"None","lastRaidEXP":2299,"lastRaidHits":28,"agressorName":"","lastRaidRanThrough":false,"lastRaidSurvived":1,"lcPointsEarned":71},{"absoluteLastTime":1756357700,"lastRaidMap":"Factory","lastRaidAs":"PMC","raidResult":"Survived","raidKills":2,"bossesKilled":0,"scavsKilled":2,"raidDamage":1024,"raidTime":1036,"discFromRaid":false,"isTransition":false,"lastRaidTransitionTo":"None","lastRaidEXP":2013,"lastRaidHits":45,"agressorName":"","lastRaidRanThrough":false,"lastRaidSurvived":1,"lcPointsEarned":43}]}